slave.sv
module slave (
    input [0:0] PCLK,
    input [0:0] PRESET,
    input [0:0] PSEL,
    input [0:0] PENABLE,
    input [0:0] PWRITE,
    input [31:0] PRWADDR,          // Master Out, Slave In
    input [31:0] PRWDATA,

    output reg [31:0] PRDATA1,     // Master In, Slave Out
    output reg [0:0] PREADY      // Slave PREADY
);

reg [3:0] state;        // Состояние конечного автомата
reg [31:0] memory [0:127];
reg [2:0] c;
reg [1:0] flag;

reg [31:0] a;
reg [31:0] b;
wire [3:0] aa;
wire [3:0] bb;
reg [0:0] s;
wire [3:0] ss;

always @(PRESET) begin

if (PRESET == 1'b1) begin
    // Сброс в начальное состояние
    state <= 4'b0000;
    PRDATA1 <= 32'b00000000000000000000000000000000;

    a = 0;
    b = 0;
    flag = 0;
    PREADY = 0;

end
end

always @(posedge PCLK)begin 

    if (PSEL == 1'b1 && PENABLE == 1'b1) begin
    case (PRWADDR)
    32'b0000_0000_0000_0000_0000_0000_0000_0000: begin
        a <= PRWDATA;
        PRDATA1 <= a;
    end
    32'b0000_0000_0000_0000_0000_0000_0000_0100: begin
        b <= PRWDATA;
        PRDATA1 <= b;
    end 
    32'b0000_0000_0000_0000_0000_0000_0000_1000: begin
        flag <= PRWDATA[0];
    end 
    endcase
    end
end

always @(posedge PCLK) begin 
    if (PRESET)begin 
        PRDATA1 <= 0;
    end
    else begin 
        if (flag == 1'b1) begin
            PRDATA1 <= 0;
            PRDATA1 <= a + b;
        end
        else begin 
            PRDATA1 <= 0;
            if (a >= b)begin 
                PRDATA1 <= a - b;
            end
            else begin 
                PRDATA1 <= -(a - b);
                PRDATA1[31] <= 1;
                //PRDATA1 <= -PRDATA1;
            end

        end
    end
end

// Логика конечного автомата
always @(posedge PCLK or posedge PRESET) begin

if (PRESET) begin
    // Сброс в начальное состояние
    state <= 4'b0000;
    PRDATA1 <= 32'b00000000000000000000000000000000;
    //data_out <= 8'b00000000;
    //miso <= 32'b00000000000000000000000000000000;
    //PREADY <= 1'b0;
end else begin    
    

    if(PSEL == 1'b1 && PENABLE == 1'b0 && PWRITE == 1'b0) begin 
        PREADY = 0; 
    end
        
    else if(PSEL == 1'b1 && PENABLE == 1'b1 && PWRITE == 1'b0) begin  
        PREADY = 1;
    end

    else if(PSEL == 1'b1 && PENABLE == 1'b0 && PWRITE == 1'b1) begin  
        //$display("if2");
        PREADY = 0; 
    end

    else if(PSEL == 1'b1 && PENABLE == 1'b1 && PWRITE == 1'b1) begin  
        PREADY = 1;
    end

    else begin
        PREADY = 0;
        //$display("if4");
    end

    end
end
endmodule

master.sv
module master (
    input [0:0] PCLK,
    input [0:0] PRESET,

    input [0:0] PSEL,
    input [0:0] PREADY,
    input [0:0] transfer,

    input [0:0] PWRITE,
    input [31:0] PADDR,
    input [31:0] PDATA, 
    output reg [0:0] PENABLE,
    output reg [31:0] PRWDATA,
    output reg [31:0] PRWADDR
);

// Регистры для хранения данных (можно добавить)
reg [31:0] memory [0:127];
reg [1:0] state = 2'b00;

// переделать в таск, для упрощения работы
task apb_read;
//input [31:0] data;
input [31:0] addr;
    begin
        //PRWDATA <= memory[addr];
        PRWDATA <= PDATA;
        //PRWDATA <= data;
        PRWADDR <= addr;
    end
endtask

task apb_write;
input [31:0] addr;
input [31:0] data;
    begin
        //memory[addr] <= data;
        PRWDATA <= data;
        PRWADDR <= addr;
    end
endtask

integer i;
reg [31:0] temp;

always @(posedge PCLK or posedge PRESET or posedge PENABLE) begin

    if (PRESET == 1'b1) begin 
        PRWDATA <= 0;
        PRWADDR <= 0;
        state = 2'b00;
        $display("PRESET");
    end

    case (state)
    2'b00:
    begin
        //memory[1] = 0; // надо изменить заполнение в форе
        //$display("startmemeoryfill");
        //$display(memory[1]);
        //if (memory[1] == 0) begin 
            //temp = 32'b00000000000000000000000000000000;
            // for (i = 0; i < 4; i = i + 1) begin
            //     memory[i] = temp;
            //     temp = temp+1;
            //     //$display(memory[1]);
            // end
        //end
        //$display(memory[1]);

        // $display("Memory contents:");
        // for (i = 0; i < 129; i = i + 1) begin
        // $display("%0h", memory[i]);
        // end

        $display("state 00");

        //заполнение памяти

        memory[0] <= 32'h00000309;  // group number
        memory[1] <= 32'h07122023;  // date
        memory[2] <= 32'h444f4c5a;  // last_name
        memory[3] <= 32'h44454e49;  // first_name

        //else begin
            //$display("(PSEL == 1'b1 && PENABLE == 1'b0)");
        PENABLE = 1'b0;
        if (PSEL == 1'b1 && transfer == 1'b1) begin 
        //$display("if accepted");
            if (PWRITE == 1'b1) begin
                state <= 2'b01;
            end
            else begin
                state <= 2'b10;
            end
        end
        //end
    end
    2'b01:
    begin
        PENABLE = 1'b1;
        $display("state 01 PWRITE");
        if (PSEL == 1'b1 && transfer == 1'b1 && PREADY == 1'b1) begin
            $display("PWRITE");
            apb_write(PADDR,PDATA);
            state <= 2'b11;
            $display("master end");
        end

    end
    2'b10:
    begin
        $display("state 10 read");
        PENABLE <= 1'b1;
        if (PSEL == 1'b1 && transfer == 1'b1 && PREADY == 1'b1) begin
            $display("read");
            apb_read(PADDR);
            state <= 2'b11;
        end

    end
    2'b11:begin
        $display("state 11");

        if (PSEL == 1'b1 && transfer == 1'b1 && PREADY == 1'b1) begin
            $display("go to PWRITE or read from acces");
            //apb_read(PADDR);
            if (PWRITE == 1'b1) begin
                state <= 2'b01;
            end
            else begin
                state <= 2'b10;
            end
        end

        if (PSEL == 1'b1 && transfer == 1'b0 && PREADY == 1'b1) begin
            $display("");
            //apb_read(PADDR);
            state <= 2'b00;
        end

        // if (PREADY == 1'b1) begin
        //     $display("");
        //     //apb_read(PADDR);
        //     state <= 2'b00;
        // end
        
        //state <= 2'b00;
        //$display("endCase");
    end
    default: begin
        //$display("no state");
    end
    endcase
end
endmodule
// изменить на PADDR и типо того

testbench.sv
`include "master.sv"
`include "slave.sv"

module testbench;

reg [0:0] PCLK;
reg [0:0] PRESET;

reg [0:0] PSEL;
reg [0:0] transfer;
reg [0:0] r;
reg [0:0] PWRITE;

reg [31:0] PADDR;
reg [31:0] PDATA;

wire [0:0] PENABLE;
wire [31:0] PRWDATA;
wire [31:0] PRWADDR;

wire [31:0] PRDATA1;
wire [0:0] PREADY;

reg [3:0] Sum_reg;     // Регистр для хранения промежуточной BCD суммы
reg [0:0] Cout_reg;    // Регистр для хранения промежуточного переноса

reg [3:0] A_reg;
reg [3:0] B_reg;
reg [0:0] Cin;
reg [1:0] f;

reg [7:0] out;
reg [0:0] carry;

master m (
    .PCLK(PCLK),
    .PRESET(PRESET),
    .PSEL(PSEL),
    .PREADY(PREADY),
    .transfer(transfer),
    .PWRITE(PWRITE),      
    .PADDR(PADDR),
    .PDATA(PDATA),

    .PENABLE(PENABLE),
    .PRWDATA(PRWDATA),
    .PRWADDR(PRWADDR)
);

slave s (
    .PCLK(PCLK),
    .PRESET(PRESET),
    .PSEL(PSEL),
    .PENABLE(PENABLE),
    .PWRITE(PWRITE),

    .PRWDATA(PRWDATA),  // master out, slave in data
    .PRWADDR(PRWADDR),  // master out, slava in addr

    .PRDATA1(PRDATA1),        // slave out data
    .PREADY(PREADY)        
);


// сначала делаем чтение в мастере,
// потом делаем передачу в слейв, где мы читаем память и изменяем
// в соответствии с заданием


initial begin

    $display("start");
    $dumpfile("testbench.vcd");
    $dumpvars(0,testbench);
    PADDR = 32'b0000_0000_0000_0000_0000_0000_0000_0000;
    PDATA = 32'b000_0000_0000_0000_0000_0000_0000_0111;

    PWRITE = 1'b1;
    
    PCLK = 1'b0;
    PRESET = 0;
    PSEL = 0;
    transfer = 1'b1;

    PRESET = 1;
    #10;

    PRESET = 0;
    PSEL = 1;
    #40;

    PSEL = 0;
    #20;

    //f = 2'b01;
    PADDR = 32'b0000_0000_0000_0000_0000_0000_0000_0100;
    PDATA = 32'b0000_0000_0000_0000_0000_0000_0000_0111;
    PSEL = 1;
    #40;
    PSEL = 0;
    #20;
    $display("-------------------f01");
    $display(PRDATA1);
    // сделать как на обратной стороне отчета

    //f = 2'b10;
    PADDR = 32'b0000_0000_0000_0000_0000_0000_0000_1000;
    PDATA = 32'b0010_0000_0000_0000_0000_0000_0000_0001;
    PSEL = 1;
    #30;
    PSEL = 0;
    #20;
    $display("-------------------f10");
    $display(PRDATA1);

    //f = 2'b11;
    PADDR = 32'b0000_0000_0000_0000_0000_0000_0000_1100;
    PDATA = 32'b0000_0000_0000_0000_0000_0000_0000_1100;
    PSEL = 1;
    #30;
    PSEL = 0;
    #20;
    $display("-------------------start");

    if (PRDATA1[31] == 1'b1) begin 
        $display("-%d",PRDATA1[30:0]);
    end
    else begin 
        $display("%d",PRDATA1[30:0]);
    end

    $display("%b",PRDATA1);

    $display("-------------------end");
    $finish;
end

always begin
    #5 PCLK = ~PCLK;
end

endmodule

testbench.vcd
$date
	Thu Dec 21 01:44:21 2023
$end
$version
	Icarus Verilog
$end
$timescale
	1s
$end
$scope module testbench $end
$var wire 32 ! PRWDATA [31:0] $end
$var wire 32 " PRWADDR [31:0] $end
$var wire 1 # PREADY $end
$var wire 32 $ PRDATA1 [31:0] $end
$var wire 1 % PENABLE $end
$var reg 32 & PADDR [31:0] $end
$var reg 1 ' PCLK $end
$var reg 32 ( PDATA [31:0] $end
$var reg 1 ) PRESET $end
$var reg 1 * PSEL $end
$var reg 1 + PWRITE $end
$var reg 1 , transfer $end
$scope module m $end
$var wire 32 - PADDR [31:0] $end
$var wire 1 ' PCLK $end
$var wire 32 . PDATA [31:0] $end
$var wire 1 ) PRESET $end
$var wire 1 * PSEL $end
$var wire 1 + PWRITE $end
$var wire 1 , transfer $end
$var wire 1 # PREADY $end
$var reg 1 % PENABLE $end
$var reg 32 / PRWADDR [31:0] $end
$var reg 32 0 PRWDATA [31:0] $end
$var reg 2 1 state [1:0] $end
$scope task apb_read $end
$var reg 32 2 addr [31:0] $end
$upscope $end
$scope task apb_write $end
$var reg 32 3 addr [31:0] $end
$var reg 32 4 data [31:0] $end
$upscope $end
$upscope $end
$scope module s $end
$var wire 1 ' PCLK $end
$var wire 1 % PENABLE $end
$var wire 1 ) PRESET $end
$var wire 32 5 PRWADDR [31:0] $end
$var wire 32 6 PRWDATA [31:0] $end
$var wire 1 * PSEL $end
$var wire 1 + PWRITE $end
$var reg 32 7 PRDATA1 [31:0] $end
$var reg 1 # PREADY $end
$var reg 32 8 a [31:0] $end
$var reg 32 9 b [31:0] $end
$var reg 2 : flag [1:0] $end
$var reg 4 ; state [3:0] $end
$upscope $end
$upscope $end
$enddefinitions $end
$comment Show the parameter values. $end
$dumpall
$end
#0
$dumpvars
b0 ;
b0 :
b0 9
b0 8
b0 7
b0 6
b0 5
bx 4
bx 3
bx 2
b0 1
b0 0
b0 /
b111 .
b0 -
1,
1+
0*
1)
b111 (
0'
b0 &
0%
b0 $
0#
b0 "
b0 !
$end
#5
1'
#10
0'
1*
0)
#15
b1 1
1'
#20
0'
#25
1%
1'
#30
0'
#35
b11 1
b111 !
b111 0
b111 6
b111 4
b0 3
1#
1'
#40
0'
#45
b1 1
b111 8
1'
#50
0'
0*
#55
b111 $
b111 7
0#
1'
#60
0'
#65
b111 $
b111 7
1'
#70
0'
1*
b100 &
b100 -
#75
b11 1
b100 "
b100 /
b100 5
b111 $
b111 7
b100 3
1#
1'
#80
0'
#85
b1 1
b111 9
b0 $
b0 7
1'
#90
0'
#95
b11 1
b0 $
b0 7
1'
#100
0'
#105
b1 1
b111 $
b111 7
1'
#110
0'
0*
#115
b0 $
b0 7
0#
1'
#120
0'
#125
1'
#130
0'
1*
b100000000000000000000000000001 (
b100000000000000000000000000001 .
b1000 &
b1000 -
#135
b11 1
b1000 "
b1000 /
b1000 5
b100000000000000000000000000001 !
b100000000000000000000000000001 0
b100000000000000000000000000001 6
b0 $
b0 7
b100000000000000000000000000001 4
b1000 3
1#
1'
#140
0'
#145
b1 1
b1 :
1'
#150
0'
#155
b11 1
b1110 $
b1110 7
1'
#160
0'
0*
#165
b1110 $
b1110 7
0#
1'
#170
0'
#175
b1110 $
b1110 7
1'
#180
0'
1*
b1100 (
b1100 .
b1100 &
b1100 -
#185
b1 1
b1110 $
b1110 7
1#
1'
#190
0'
#195
b11 1
b1100 "
b1100 /
b1100 5
b1100 !
b1100 0
b1100 6
b1110 $
b1110 7
b1100 4
b1100 3
1'
#200
0'
#205
b1 1
b1110 $
b1110 7
1'
#210
0'
0*
#215
b1110 $
b1110 7
0#
1'
#220
0'
#225
b1110 $
b1110 7
1'
