slave.sv
module slave (
    input [0:0] PCLK,
    input [0:0] PRESET,
    input [0:0] PSEL,
    input [0:0] PENABLE,
    input [0:0] PWRITE,
    input [31:0] PRWADDR,          // Master Out, Slave In
    input [31:0] PRWDATA,
    input [1:0] f,

    output reg [31:0] PRDATA1,     // Master In, Slave Out
    output reg [0:0] PREADY      // Slave PREADY
);

//reg [31:0] data_in;     // Входные данные от мастера
//reg [31:0] data_out;    // Выходные данные для слейва
reg [3:0] state;        // Состояние конечного автомата
reg [31:0] memory [0:127];
reg [2:0] c;

reg [31:0] a;
reg [31:0] b;
wire [3:0] aa;
wire [3:0] bb;
reg [0:0] s;
wire [3:0] ss;


// task apb_read;
// input [31:0] addr;
//     begin
//         out_data <= memory[addr];
//     end
// endtask

// task apb_write;
// input [31:0] addr;
// input [31:0] data;
//     begin
//         memory[addr] <= data;
//     end
// endtask
always @(PRESET) begin

if (PRESET == 1'b1) begin
    // Сброс в начальное состояние
    state <= 4'b0000;
    PRDATA1 <= 32'b00000000000000000000000000000000;
    //data_out <= 8'b00000000;
    //miso <= 32'b00000000000000000000000000000000;
    //PREADY <= 1'b0;
    a = 0;
    b = 0;
    PREADY = 0;

    // memory[0] <= 32'h00000309;  // group number
    // memory[1] <= 32'h07122023;  // date
    // memory[2] <= 32'h444f4c5a;  // last_name
    // memory[3] <= 32'h44454e49;  // first_name

end
end


// Логика конечного автомата
always @(posedge PCLK or posedge PRESET) begin

if (PRESET) begin
    // Сброс в начальное состояние
    state <= 4'b0000;
    PRDATA1 <= 32'b00000000000000000000000000000000;
    //data_out <= 8'b00000000;
    //miso <= 32'b00000000000000000000000000000000;
    //PREADY <= 1'b0;
end else begin    
    
    //$display("in slave");

    if(PSEL == 1'b1 && PENABLE == 1'b1 && f == 2'b01) begin  
        // a[0] <= PRWDATA[0];
        // a[1] <= PRWDATA[1];
        // a[2] <= PRWDATA[2];
        // a[3] <= PRWDATA[3];
        a <= PRWDATA;
        PRDATA1 <= a;

        $display("a:");
        $display(a);
    end

    if(PSEL == 1'b1 && PENABLE == 1'b1 && f == 2'b10) begin  
        // b[0] <= PRWDATA[0];
        // b[1] <= PRWDATA[1];
        // b[2] <= PRWDATA[2];
        // b[3] <= PRWDATA[3];
        b <= PRWDATA;
        PRDATA1 <= b;

        $display("b:");
        $display(b);

    end

    if(PSEL == 1'b1 && PENABLE == 1'b1 && f == 2'b11) begin  

        // PRDATA1 = a | b; 
        // PRDATA1 = PRDATA1 + (a & b);
        // $display("%b",a);
        // $display("%b",b);
        // $display("%b",PRDATA1);
        PRDATA1 = 0;

        PRDATA1[0] = ((~a[0] & b[0]) | (a[0] & ~b[0]));
        $display("------------ start ------------");
        // $display("%b",a);
        // $display("%b",b);
        // $display("%b",PRDATA1);
        s = a[0] & b[0];

        for (integer i = 1;i < 32; i = i + 1) begin
            PRDATA1[i] = ((~((~a[i] & b[i]) | (a[i] & ~b[i])) & s) | (((~a[i] & b[i]) | (a[i] & ~b[i])) & ~s));
            s = (a[i] & b[i]) | (a[i] & s) | (b[i] & s);
        end
        // $display("%b",a);
        // $display("%b",b);
        // $display("%b",PRDATA1);

        // PRDATA1[2] = ((~((~a[2] & b[2]) | (a[2] & ~b[2])) & s) | (((~a[2] & b[2]) | (a[2] & ~b[2])) & ~s));
        // s =(a[2] & b[2]) | (a[2] & s) | (b[2] & s);

        // $display("%b",a);
        // $display("%b",b);
        // $display("%b",PRDATA1);

        // PRDATA1[3] = ((~((~a[3] & b[3]) | (a[3] & ~b[3])) & s) | (((~a[3] & b[3]) | (a[3] & ~b[3])) & ~s));
        // s = (a[3] & b[3]) | (a[3] & s) | (b[3] & s);

        $display("a: %b",a);
        $display("b: %b",b);
        $display("result: %b",PRDATA1);

        $display("a: %d",a);
        $display("b: %d",b);
        $display("result: %d",PRDATA1);



        //PRDATA1 = a + b;

        // $display("PRDATA1:");
        // $display(PRDATA1);
        $display("------------ end ------------");
    end

    if(PSEL == 1'b1 && PENABLE == 1'b0 && PWRITE == 1'b0) begin 
        //$display("if1");
        PREADY = 0; 
    end
        
    else if(PSEL == 1'b1 && PENABLE == 1'b1 && PWRITE == 1'b0) begin  
        //$display("wriite in slave");
        //PRDATA1 <= memory[PRWADDR];
        PREADY = 1;
    end

    else if(PSEL == 1'b1 && PENABLE == 1'b0 && PWRITE == 1'b1) begin  
        //$display("if2");
        PREADY = 0; 
    end

    else if(PSEL == 1'b1 && PENABLE == 1'b1 && PWRITE == 1'b1) begin  
        //$display("if3");
        PREADY = 1;
        //PRDATA1 <= PRWDATA;
        //memory[PRWADDR] <= PRWDATA;
    end

    else begin
        PREADY = 0;
        //$display("if4");
    end

    // $display("after slave -----------");
    // $display(PREADY);
    // $display(PENABLE);
    // $display(PWRITE);
    // $display("after slave ^^^^^^^^^^");
    end
end
endmodule

master.sv
module master (
    input [0:0] PCLK,
    input [0:0] PRESET,

    input [0:0] PSEL,
    input [0:0] PREADY,
    input [0:0] transfer,

    input [0:0] PWRITE,
    input [31:0] PADDR,
    input [31:0] PDATA, 
    output reg [0:0] PENABLE,
    output reg [31:0] PRWDATA,
    output reg [31:0] PRWADDR
);

// Регистры для хранения данных (можно добавить)
reg [31:0] memory [0:127];
reg [1:0] state = 2'b00;

// переделать в таск, для упрощения работы
task apb_read;
//input [31:0] data;
input [31:0] addr;
    begin
        //PRWDATA <= memory[addr];
        PRWDATA <= PDATA;
        //PRWDATA <= data;
        PRWADDR <= addr;
    end
endtask

task apb_write;
input [31:0] addr;
input [31:0] data;
    begin
        //memory[addr] <= data;
        PRWDATA <= data;
        PRWADDR <= addr;
    end
endtask

integer i;
reg [31:0] temp;

always @(posedge PCLK or posedge PRESET or posedge PENABLE) begin

    if (PRESET == 1'b1) begin 
        PRWDATA <= 0;
        PRWADDR <= 0;
        state = 2'b00;
        $display("PRESET");
    end

    case (state)
    2'b00:
    begin
        //memory[1] = 0; // надо изменить заполнение в форе
        //$display("startmemeoryfill");
        //$display(memory[1]);
        //if (memory[1] == 0) begin 
            //temp = 32'b00000000000000000000000000000000;
            // for (i = 0; i < 4; i = i + 1) begin
            //     memory[i] = temp;
            //     temp = temp+1;
            //     //$display(memory[1]);
            // end
        //end
        //$display(memory[1]);

        // $display("Memory contents:");
        // for (i = 0; i < 129; i = i + 1) begin
        // $display("%0h", memory[i]);
        // end

        $display("state 00");

        //заполнение памяти

        memory[0] <= 32'h00000309;  // group number
        memory[1] <= 32'h07122023;  // date
        memory[2] <= 32'h444f4c5a;  // last_name
        memory[3] <= 32'h44454e49;  // first_name

        //else begin
            //$display("(PSEL == 1'b1 && PENABLE == 1'b0)");
        PENABLE = 1'b0;
        if (PSEL == 1'b1 && transfer == 1'b1) begin 
        //$display("if accepted");
            if (PWRITE == 1'b1) begin
                state <= 2'b01;
            end
            else begin
                state <= 2'b10;
            end
        end
        //end
    end
    2'b01:
    begin
        PENABLE = 1'b1;
        $display("state 01 PWRITE");
        if (PSEL == 1'b1 && transfer == 1'b1 && PREADY == 1'b1) begin
            $display("PWRITE");
            apb_write(PADDR,PDATA);
            state <= 2'b11;
            $display("master end");
        end

    end
    2'b10:
    begin
        $display("state 10 read");
        PENABLE <= 1'b1;
        if (PSEL == 1'b1 && transfer == 1'b1 && PREADY == 1'b1) begin
            $display("read");
            apb_read(PADDR);
            state <= 2'b11;
        end

    end
    2'b11:begin
        $display("state 11");

        if (PSEL == 1'b1 && transfer == 1'b1 && PREADY == 1'b1) begin
            $display("go to PWRITE or read from acces");
            //apb_read(PADDR);
            if (PWRITE == 1'b1) begin
                state <= 2'b01;
            end
            else begin
                state <= 2'b10;
            end
        end

        if (PSEL == 1'b1 && transfer == 1'b0 && PREADY == 1'b1) begin
            $display("");
            //apb_read(PADDR);
            state <= 2'b00;
        end

        // if (PREADY == 1'b1) begin
        //     $display("");
        //     //apb_read(PADDR);
        //     state <= 2'b00;
        // end
        
        //state <= 2'b00;
        //$display("endCase");
    end
    default: begin
        //$display("no state");
    end
    endcase
end
endmodule
// изменить на PADDR и типо того

testbench.sv
`include "master.sv"
`include "slave.sv"

module testbench;

reg [0:0] PCLK;
reg [0:0] PRESET;

reg [0:0] PSEL;
reg [0:0] transfer;
reg [0:0] r;
reg [0:0] PWRITE;

reg [31:0] PADDR;
reg [31:0] PDATA;

wire [0:0] PENABLE;
wire [31:0] PRWDATA;
wire [31:0] PRWADDR;

wire [31:0] PRDATA1;
wire [0:0] PREADY;

reg [3:0] Sum_reg;     // Регистр для хранения промежуточной BCD суммы
reg [0:0] Cout_reg;    // Регистр для хранения промежуточного переноса

reg [3:0] A_reg;
reg [3:0] B_reg;
reg [0:0] Cin;
reg [1:0] f;

reg [7:0] out;
reg [0:0] carry;

master m (
    .PCLK(PCLK),
    .PRESET(PRESET),
    .PSEL(PSEL),
    .PREADY(PREADY),
    .transfer(transfer),
    .PWRITE(PWRITE),      
    .PADDR(PADDR),
    .PDATA(PDATA),

    .PENABLE(PENABLE),
    .PRWDATA(PRWDATA),
    .PRWADDR(PRWADDR)
);

slave s (
    .PCLK(PCLK),
    .PRESET(PRESET),
    .PSEL(PSEL),
    .PENABLE(PENABLE),
    .PWRITE(PWRITE),
    .f(f),

    .PRWDATA(PRWDATA),  // master out, slave in data
    .PRWADDR(PRWADDR),  // master out, slava in addr

    .PRDATA1(PRDATA1),        // slave out data
    .PREADY(PREADY)        
);


// сначала делаем чтение в мастере,
// потом делаем передачу в слейв, где мы читаем память и изменяем
// в соответствии с заданием


initial begin

    $display("start");
    $dumpfile("testbench.vcd");
    $dumpvars(0,testbench);
    PADDR = 32'b00000000000000000000000000000000;
    PDATA = 32'h00000309;

    PWRITE = 1'b1;
    
    PCLK = 1'b0;
    PRESET = 0;
    PSEL = 0;
    transfer = 1'b1;

    PRESET = 1;
    #10;

    PRESET = 0;
    PSEL = 1;
    #40;

    PSEL = 0;
    #20;

    f = 2'b01;
    PADDR = 32'b0000_0000_0000_0000_0000_0000_0000_0100;
    PDATA = 32'b0011_0000_0000_0000_0000_0000_0000_0011;
    PSEL = 1;
    #40;
    PSEL = 0;
    #20;
    $display("-------------------f01");
    $display(PRDATA1);

    f = 2'b10;
    PADDR = 32'b0000_0000_0000_0000_0000_0000_0000_1000;
    PDATA = 32'b0011_0000_0000_0000_0000_0000_0000_0111;
    PSEL = 1;
    #30;
    PSEL = 0;
    #20;
    $display("-------------------f10");
    $display(PRDATA1);

    f = 2'b11;
    PADDR = 32'b0000_0000_0000_0000_0000_0000_0000_1100;
    PDATA = 32'b0000_0000_0000_0000_0000_0000_0000_1100;
    PSEL = 1;
    #30;
    PSEL = 0;
    #20;
    $display("-------------------start");

    $display(PRDATA1);

    $display("-------------------end");
    $finish;
end

always begin
    #5 PCLK = ~PCLK;
end

endmodule

testbench.vcd
$date
	Thu Dec 14 12:22:45 2023
$end
$version
	Icarus Verilog
$end
$timescale
	1s
$end
$scope module testbench $end
$var wire 32 ! PRWDATA [31:0] $end
$var wire 32 " PRWADDR [31:0] $end
$var wire 1 # PREADY $end
$var wire 32 $ PRDATA1 [31:0] $end
$var wire 1 % PENABLE $end
$var reg 32 & PADDR [31:0] $end
$var reg 1 ' PCLK $end
$var reg 32 ( PDATA [31:0] $end
$var reg 1 ) PRESET $end
$var reg 1 * PSEL $end
$var reg 1 + PWRITE $end
$var reg 2 , f [1:0] $end
$var reg 1 - transfer $end
$scope module m $end
$var wire 32 . PADDR [31:0] $end
$var wire 1 ' PCLK $end
$var wire 32 / PDATA [31:0] $end
$var wire 1 ) PRESET $end
$var wire 1 * PSEL $end
$var wire 1 + PWRITE $end
$var wire 1 - transfer $end
$var wire 1 # PREADY $end
$var reg 1 % PENABLE $end
$var reg 32 0 PRWADDR [31:0] $end
$var reg 32 1 PRWDATA [31:0] $end
$var reg 2 2 state [1:0] $end
$scope task apb_read $end
$var reg 32 3 addr [31:0] $end
$upscope $end
$scope task apb_write $end
$var reg 32 4 addr [31:0] $end
$var reg 32 5 data [31:0] $end
$upscope $end
$upscope $end
$scope module s $end
$var wire 1 ' PCLK $end
$var wire 1 % PENABLE $end
$var wire 1 ) PRESET $end
$var wire 32 6 PRWADDR [31:0] $end
$var wire 32 7 PRWDATA [31:0] $end
$var wire 1 * PSEL $end
$var wire 1 + PWRITE $end
$var wire 2 8 f [1:0] $end
$var reg 32 9 PRDATA1 [31:0] $end
$var reg 1 # PREADY $end
$var reg 32 : a [31:0] $end
$var reg 32 ; b [31:0] $end
$var reg 1 < s $end
$var reg 4 = state [3:0] $end
$scope begin $ivl_for_loop0 $end
$var integer 32 > i [31:0] $end
$upscope $end
$upscope $end
$upscope $end
$enddefinitions $end
$comment Show the parameter values. $end
$dumpall
$end
#0
$dumpvars
bx >
b0 =
x<
b0 ;
b0 :
b0 9
bx 8
b0 7
b0 6
bx 5
bx 4
bx 3
b0 2
b0 1
b0 0
b1100001001 /
b0 .
1-
bx ,
1+
0*
1)
b1100001001 (
0'
b0 &
0%
b0 $
0#
b0 "
b0 !
$end
#5
1'
#10
0'
1*
0)
#15
b1 2
1'
#20
0'
#25
1%
1'
#30
0'
#35
b11 2
b1100001001 !
b1100001001 1
b1100001001 7
b1100001001 5
b0 4
1#
1'
#40
0'
#45
b1 2
1'
#50
0'
0*
#55
0#
1'
#60
0'
#65
1'
#70
0'
1*
b110000000000000000000000000011 (
b110000000000000000000000000011 /
b100 &
b100 .
b1 ,
b1 8
#75
b11 2
b100 "
b100 0
b100 6
b110000000000000000000000000011 !
b110000000000000000000000000011 1
b110000000000000000000000000011 7
b1100001001 :
b110000000000000000000000000011 5
b100 4
1#
1'
#80
0'
#85
b1 2
b1100001001 $
b1100001001 9
b110000000000000000000000000011 :
1'
#90
0'
#95
b11 2
b110000000000000000000000000011 $
b110000000000000000000000000011 9
1'
#100
0'
#105
b1 2
1'
#110
0'
0*
#115
0#
1'
#120
0'
#125
1'
#130
0'
1*
b110000000000000000000000000111 (
b110000000000000000000000000111 /
b1000 &
b1000 .
b10 ,
b10 8
#135
b11 2
b1000 "
b1000 0
b1000 6
b110000000000000000000000000111 !
b110000000000000000000000000111 1
b110000000000000000000000000111 7
b0 $
b0 9
b110000000000000000000000000011 ;
b110000000000000000000000000111 5
b1000 4
1#
1'
#140
0'
#145
b1 2
b110000000000000000000000000011 $
b110000000000000000000000000011 9
b110000000000000000000000000111 ;
1'
#150
0'
#155
b11 2
b110000000000000000000000000111 $
b110000000000000000000000000111 9
1'
#160
0'
0*
#165
0#
1'
#170
0'
#175
1'
#180
0'
1*
b1100 (
b1100 /
b1100 &
b1100 .
b11 ,
b11 8
#185
b1 2
1#
b100000 >
0<
b1100000000000000000000000001010 $
b1100000000000000000000000001010 9
1'
#190
0'
#195
b11 2
b1100 "
b1100 0
b1100 6
b1100 !
b1100 1
b1100 7
b1100 5
b1100 4
b100000 >
0<
b1100000000000000000000000001010 $
b1100000000000000000000000001010 9
1'
#200
0'
#205
b1 2
b100000 >
0<
b1100000000000000000000000001010 $
b1100000000000000000000000001010 9
1'
#210
0'
0*
#215
0#
1'
