slave.sv
module slave (
    input [0:0] PCLK,
    input [0:0] PRESET,
    input [0:0] PSEL,
    input [0:0] PENABLE,
    input [0:0] PWRITE,
    input [31:0] PRWADDR,          // Master Out, Slave In
    input [31:0] PRWDATA,
    output reg [31:0] PRDATA1,     // Master In, Slave Out
    output reg [0:0] PREADY      // Slave PREADY
);

//reg [31:0] data_in;     // Входные данные от мастера
//reg [31:0] data_out;    // Выходные данные для слейва
reg [3:0] state;        // Состояние конечного автомата
reg [31:0] memory [0:127];
reg [2:0] c;


// task apb_read;
// input [31:0] addr;
//     begin
//         out_data <= memory[addr];
//     end
// endtask

// task apb_write;
// input [31:0] addr;
// input [31:0] data;
//     begin
//         memory[addr] <= data;
//     end
// endtask
always @(PRESET) begin

if (PRESET == 1'b1) begin
    // Сброс в начальное состояние
    state <= 4'b0000;
    PRDATA1 <= 32'b00000000000000000000000000000000;
    //data_out <= 8'b00000000;
    //miso <= 32'b00000000000000000000000000000000;
    //PREADY <= 1'b0;

    PREADY = 0;

    memory[0] <= 32'h00000309;  // group number
    memory[1] <= 32'h07122023;  // date
    memory[2] <= 32'h444f4c5a;  // last_name
    memory[3] <= 32'h44454e49;  // first_name

end
end


// Логика конечного автомата
always @(posedge PCLK or posedge PRESET) begin

if (PRESET) begin
    // Сброс в начальное состояние
    state <= 4'b0000;
    PRDATA1 <= 32'b00000000000000000000000000000000;
    //data_out <= 8'b00000000;
    //miso <= 32'b00000000000000000000000000000000;
    //PREADY <= 1'b0;
end else begin    
    
    $display("in slave");

    if(PSEL == 1'b1 && PENABLE == 1'b0 && PWRITE == 1'b0) begin 
        $display("if1");
        PREADY = 0; 
    end
        
    else if(PSEL == 1'b1 && PENABLE == 1'b1 && PWRITE == 1'b0) begin  
        $display("wriite in slave");
        PRDATA1 <= memory[PRWADDR];
        PREADY = 1;
    end

    else if(PSEL == 1'b1 && PENABLE == 1'b0 && PWRITE == 1'b1) begin  
        $display("if2");
        PREADY = 0; 
    end

    else if(PSEL == 1'b1 && PENABLE == 1'b1 && PWRITE == 1'b1) begin  
        $display("if3");
        PREADY = 1;
        PRDATA1 <= PRWDATA;
        memory[PRWADDR] <= PRWDATA;
        c = c + 1;
    end

    else begin
        PREADY = 0;
        $display("if4");
    end

    // $display("after slave -----------");
    // $display(PREADY);
    // $display(PENABLE);
    // $display(PWRITE);
    // $display("after slave ^^^^^^^^^^");
    end
end
endmodule

master.sv
module master (
    input [0:0] PCLK,
    input [0:0] PRESET,

    input [0:0] PSEL,
    input [0:0] PREADY,
    input [0:0] transfer,

    input [0:0] PWRITE,
    input [31:0] PADDR,
    input [31:0] PDATA, 
    output reg [0:0] PENABLE,
    output reg [31:0] PRWDATA,
    output reg [31:0] PRWADDR
);

// Регистры для хранения данных (можно добавить)
reg [31:0] memory [0:127];
reg [1:0] state = 2'b00;

// переделать в таск, для упрощения работы
task apb_read;
//input [31:0] data;
input [31:0] addr;
    begin
        //PRWDATA <= memory[addr];
        PRWDATA <= PDATA;
        //PRWDATA <= data;
        PRWADDR <= addr;
    end
endtask

task apb_write;
input [31:0] addr;
input [31:0] data;
    begin
        //memory[addr] <= data;
        PRWDATA <= data;
        PRWADDR <= addr;
    end
endtask

integer i;
reg [31:0] temp;

always @(posedge PCLK or posedge PRESET or posedge PENABLE) begin

    if (PRESET == 1'b1) begin 
        PRWDATA <= 0;
        PRWADDR <= 0;
        state = 2'b00;
        $display("PRESET");
    end

    case (state)
    2'b00:
    begin
        //memory[1] = 0; // надо изменить заполнение в форе
        //$display("startmemeoryfill");
        //$display(memory[1]);
        //if (memory[1] == 0) begin 
            //temp = 32'b00000000000000000000000000000000;
            // for (i = 0; i < 4; i = i + 1) begin
            //     memory[i] = temp;
            //     temp = temp+1;
            //     //$display(memory[1]);
            // end
        //end
        //$display(memory[1]);

        // $display("Memory contents:");
        // for (i = 0; i < 129; i = i + 1) begin
        // $display("%0h", memory[i]);
        // end

        $display("state 00");

        //заполнение памяти

        memory[0] <= 32'h00000309;  // group number
        memory[1] <= 32'h07122023;  // date
        memory[2] <= 32'h444f4c5a;  // last_name
        memory[3] <= 32'h44454e49;  // first_name

        //else begin
            //$display("(PSEL == 1'b1 && PENABLE == 1'b0)");
        PENABLE = 1'b0;
        if (PSEL == 1'b1 && transfer == 1'b1) begin 
        //$display("if accepted");
            if (PWRITE == 1'b1) begin
                state <= 2'b01;
            end
            else begin
                state <= 2'b10;
            end
        end
        //end
    end
    2'b01:
    begin
        PENABLE = 1'b1;
        $display("state 01 PWRITE");
        if (PSEL == 1'b1 && transfer == 1'b1 && PREADY == 1'b1) begin
            $display("PWRITE");
            apb_write(PADDR,PDATA);
            state <= 2'b11;
            $display("master end");
        end

    end
    2'b10:
    begin
        $display("state 10 read");
        PENABLE <= 1'b1;
        if (PSEL == 1'b1 && transfer == 1'b1 && PREADY == 1'b1) begin
            $display("read");
            apb_read(PADDR);
            state <= 2'b11;
        end

    end
    2'b11:begin
        $display("state 11");

        if (PSEL == 1'b1 && transfer == 1'b1 && PREADY == 1'b1) begin
            $display("go to PWRITE or read from acces");
            //apb_read(PADDR);
            if (PWRITE == 1'b1) begin
                state <= 2'b01;
            end
            else begin
                state <= 2'b10;
            end
        end

        if (PSEL == 1'b1 && transfer == 1'b0 && PREADY == 1'b1) begin
            $display("");
            //apb_read(PADDR);
            state <= 2'b00;
        end

        // if (PREADY == 1'b1) begin
        //     $display("");
        //     //apb_read(PADDR);
        //     state <= 2'b00;
        // end
        
        //state <= 2'b00;
        //$display("endCase");
    end
    default: begin
        //$display("no state");
    end
    endcase
end
endmodule
// изменить на PADDR и типо того

testbench.sv
`include "master.sv"
`include "slave.sv"

module testbench;

reg [0:0] PCLK;
reg [0:0] PRESET;
//reg [0:0] mready;

reg [0:0] PSEL;
reg [0:0] transfer;
reg [0:0] r;
reg [0:0] PWRITE;

reg [31:0] PADDR;
reg [31:0] PDATA;

// reg [31:0] inp_addr;
// reg [31:0] inp_data;


wire [0:0] PENABLE;
wire [31:0] PRWDATA;
wire [31:0] PRWADDR;

//reg [31:0] sin_data;
//wire [31:0] sout_data;
wire [31:0] PRDATA1;
wire [0:0] PREADY;

master m (
    .PCLK(PCLK),
    .PRESET(PRESET),
    .PSEL(PSEL),
    .PREADY(PREADY),
    .transfer(transfer),
    .PWRITE(PWRITE),      
    .PADDR(PADDR),
    .PDATA(PDATA),

    .PENABLE(PENABLE),
    .PRWDATA(PRWDATA),
    .PRWADDR(PRWADDR)
);

slave s (
    .PCLK(PCLK),
    .PRESET(PRESET),
    .PSEL(PSEL),
    .PENABLE(PENABLE),
    .PWRITE(PWRITE),

    .PRWDATA(PRWDATA),  // master out, slave in data
    .PRWADDR(PRWADDR),  // master out, slava in addr

    .PRDATA1(PRDATA1),        // slave out data
    .PREADY(PREADY)        
);


// сначала делаем чтение в мастере,
// потом делаем передачу в слейв, где мы читаем память и изменяем
// в соответствии с заданием


initial begin

    $display("start");
    $dumpfile("testbench.vcd");
    $dumpvars(0,testbench);
    PADDR = 32'b00000000000000000000000000000010;
    PDATA = 32'b00000000000000000000000000001111;
    //out_data = 32'b00000000000000000000000000000000;
               //32'b00000000000000000000000000000000s
    //sin_data = 32'b10000000000000000000000000000011;

    PWRITE = 1'b0;
    
    PCLK = 1'b0;
    PRESET = 0;
    PSEL = 0;
    //enable = 0;
    transfer = 1'b1;
    //ready = 0;
    //mready = 1'b0;

    PRESET = 1;
    #10;
    $display("11");

    PRESET = 0;
    PSEL = 1;
    #10;
    $display("12");

    //enable = 1;
    #10;
    $display("13");

    //mready = 1;
    #10;
    $display("14");
    $display(PENABLE);
    $display(PSEL);
    $display(PREADY);
    $display(PRWDATA);
    $display(PRDATA1);



    //mready = 0;
    #10;
    $display("15");
    $display(PRDATA1);


    PSEL = 0;
    #10;
    $display("16");

    //enable = 0;
    #10;
    $display("17");

    PRESET = 1;
    #10;
    $display("18");

    PRESET = 0;
    #10;
    $display("19");


    $display("end");
    $finish;
end

always begin
    #5 PCLK = ~PCLK;
end

endmodule

testbench.vcd
$date
	Sun Dec 10 19:33:03 2023
$end
$version
	Icarus Verilog
$end
$timescale
	1s
$end
$scope module testbench $end
$var wire 32 ! PRWDATA [31:0] $end
$var wire 32 " PRWADDR [31:0] $end
$var wire 1 # PREADY $end
$var wire 32 $ PRDATA1 [31:0] $end
$var wire 1 % PENABLE $end
$var reg 32 & PADDR [31:0] $end
$var reg 1 ' PCLK $end
$var reg 32 ( PDATA [31:0] $end
$var reg 1 ) PRESET $end
$var reg 1 * PSEL $end
$var reg 1 + PWRITE $end
$var reg 1 , transfer $end
$scope module m $end
$var wire 32 - PADDR [31:0] $end
$var wire 1 ' PCLK $end
$var wire 32 . PDATA [31:0] $end
$var wire 1 ) PRESET $end
$var wire 1 * PSEL $end
$var wire 1 + PWRITE $end
$var wire 1 , transfer $end
$var wire 1 # PREADY $end
$var reg 1 % PENABLE $end
$var reg 32 / PRWADDR [31:0] $end
$var reg 32 0 PRWDATA [31:0] $end
$var reg 2 1 state [1:0] $end
$scope task apb_read $end
$var reg 32 2 addr [31:0] $end
$upscope $end
$scope task apb_write $end
$var reg 32 3 addr [31:0] $end
$var reg 32 4 data [31:0] $end
$upscope $end
$upscope $end
$scope module s $end
$var wire 1 ' PCLK $end
$var wire 1 % PENABLE $end
$var wire 1 ) PRESET $end
$var wire 32 5 PRWADDR [31:0] $end
$var wire 32 6 PRWDATA [31:0] $end
$var wire 1 * PSEL $end
$var wire 1 + PWRITE $end
$var reg 32 7 PRDATA1 [31:0] $end
$var reg 1 # PREADY $end
$var reg 3 8 c [2:0] $end
$var reg 4 9 state [3:0] $end
$upscope $end
$upscope $end
$enddefinitions $end
$comment Show the parameter values. $end
$dumpall
$end
#0
$dumpvars
b0 9
bx 8
b0 7
b0 6
b0 5
bx 4
bx 3
bx 2
b0 1
b0 0
b0 /
b1111 .
b10 -
1,
0+
0*
1)
b1111 (
0'
b10 &
0%
b0 $
0#
b0 "
b0 !
$end
#5
1'
#10
0'
1*
0)
#15
b10 1
1'
#20
0'
#25
1%
1'
#30
0'
#35
b11 1
b10 "
b10 /
b10 5
b1111 !
b1111 0
b1111 6
b1100001001 $
b1100001001 7
b10 2
1#
1'
#40
0'
#45
b10 1
b1000100010011110100110001011010 $
b1000100010011110100110001011010 7
1'
#50
0'
0*
#55
0#
1'
#60
0'
#65
1'
#70
b0 "
b0 /
b0 5
b0 !
b0 0
b0 6
b0 $
b0 7
0%
b0 1
0'
1)
#75
1'
#80
0'
0)
